candypen/__init__.py
candypen/core.py
candypen/decorators.py
candypen/examples.py
candypen/utils.py
candypen/templates/process_template.py
candypen/templates/thread_template.py
candypen-0.0.1.dist-info/LICENSE
candypen-0.0.1.dist-info/METADATA
candypen-0.0.1.dist-info/WHEEL
candypen-0.0.1.dist-info/entry_points.txt
candypen-0.0.1.dist-info/top_level.txt
candypen-0.0.1.dist-info/RECORD
