Metadata-Version: 2.1
Name: candypen
Version: 0.0.1
Summary: A tiny tool module for multi-process programs.
Home-page: UNKNOWN
Author: candyriver
Author-email: 
License: UNKNOWN
Platform: UNKNOWN
Classifier: Programming Language :: Python :: 3
Classifier: Programming Language :: Python :: 3.5
Classifier: Programming Language :: Python :: 3.6
Classifier: Programming Language :: Python :: 3.7
Classifier: Programming Language :: Python :: 3.8
Classifier: Programming Language :: Python :: 3.9
Classifier: License :: OSI Approved :: MIT License
Classifier: Operating System :: OS Independent
Requires-Dist: termcolor (>=1.1.0)
Requires-Dist: requests (>=2.24.0)
Requires-Dist: colorama (>=0.4.4)
